financialyear/__init__.py
financialyear/src/__init__.py
financialyear/src/main.py
financialyear/src/primary.py
financialyear-1.3.dist-info/LICENSE
financialyear-1.3.dist-info/METADATA
financialyear-1.3.dist-info/WHEEL
financialyear-1.3.dist-info/top_level.txt
financialyear-1.3.dist-info/RECORD
