Metadata-Version: 2.1
Name: financialyear
Version: 1.3
Summary: It Calculate financial year related dates
Home-page: https://github.com/piidus/FinancialYear
Author: Sudiip
Author-email: sudiipkumarbasu@gmail.com
Keywords: financial year,fin year
License-File: LICENSE
